PowerWrapper/__init__.py
PowerWrapper/errors.py
PowerWrapper/maths.py
PowerWrapper/system.py
PowerWrapper-0.0.7.dist-info/LICENSE
PowerWrapper-0.0.7.dist-info/METADATA
PowerWrapper-0.0.7.dist-info/WHEEL
PowerWrapper-0.0.7.dist-info/top_level.txt
PowerWrapper-0.0.7.dist-info/RECORD
