Metadata-Version: 2.1
Name: PowerWrapper
Version: 0.0.7
Summary: A powerful library that wraps advanced functions.
Home-page: 
Author: SapphireKR
Author-email: sapphirekr11@protonmail.com
License: MIT
Keywords: python,wrapper
Classifier: Development Status :: 5 - Production/Stable
Classifier: Intended Audience :: Education
Classifier: Operating System :: Microsoft :: Windows :: Windows 10
Classifier: License :: OSI Approved :: GNU General Public License v3 (GPLv3)
Classifier: Programming Language :: Python :: 3
License-File: LICENSE
